mcp_snowflake_server/__init__.py
mcp_snowflake_server/db_client.py
mcp_snowflake_server/server.py
mcp_snowflake_server/write_detector.py
mcp_snowflake_server_readonly-0.4.6.dist-info/METADATA
mcp_snowflake_server_readonly-0.4.6.dist-info/WHEEL
mcp_snowflake_server_readonly-0.4.6.dist-info/entry_points.txt
mcp_snowflake_server_readonly-0.4.6.dist-info/licenses/LICENSE
mcp_snowflake_server_readonly-0.4.6.dist-info/RECORD
