Metadata-Version: 2.4
Name: mcp_snowflake_server_readonly
Version: 0.4.6
Summary: A simple Snowflake MCP server
License-File: LICENSE
Requires-Python: <3.13,>=3.10
Requires-Dist: mcp>=1.0.0
Requires-Dist: pandas>=2.2.3
Requires-Dist: python-dotenv>=1.0.1
Requires-Dist: snowflake-connector-python[pandas]<3.14.0,>=3.12.0
Requires-Dist: snowflake-snowpark-python>=1.26.0
Requires-Dist: sqlparse>=0.5.3
